sc_retail_post_rpa/__init__.py
sc_retail_post_rpa/main.py
sc_retail_post_rpa/rpa/__init__.py
sc_retail_post_rpa/rpa/analyzer.py
sc_retail_post_rpa/tests/__init__.py
sc_retail_post_rpa/tests/sample_config/production.yml
sc_retail_post_rpa-0.0.7.dist-info/LICENSE
sc_retail_post_rpa-0.0.7.dist-info/METADATA
sc_retail_post_rpa-0.0.7.dist-info/WHEEL
sc_retail_post_rpa-0.0.7.dist-info/entry_points.txt
sc_retail_post_rpa-0.0.7.dist-info/top_level.txt
sc_retail_post_rpa-0.0.7.dist-info/RECORD
