Metadata-Version: 2.1
Name: sc-retail-post-rpa
Version: 0.0.7
Summary: RPA process after retail analysis
Home-page: https://github.com/Scott-Lau/sc-retail-post-rpa
Author: Scott Lau
Author-email: exceedego@126.com
License: MIT
Keywords: RPA Retail
Platform: POSIX
Classifier: Programming Language :: Python :: 3
Classifier: Programming Language :: Python :: 3.6
Classifier: Programming Language :: Python :: 3.7
Classifier: Programming Language :: Python :: 3.8
Classifier: Programming Language :: Python :: 3.9
Classifier: License :: OSI Approved :: MIT License
Classifier: Operating System :: OS Independent
Classifier: Topic :: Software Development
Classifier: Topic :: Utilities
Requires-Python: >=3.6
License-File: LICENSE
Requires-Dist: sc-utilities (>=0.0.7)
Requires-Dist: sc-config (>=0.0.11)
Requires-Dist: sc-retail-analysis (>=0.0.38)
Requires-Dist: python-dateutil (>=2.8.1)
